{"nodes": [{"id": "routes_notifications_routes", "label": "Notification Routes", "file_type": "code", "source_file": "app/notifications/routes.py", "source_location": null, "source_url": null, "captured_at": null, "author": null, "contributor": null}, {"id": "routes_notifications_send", "label": "notifications.send", "file_type": "code", "source_file": "app/notifications/routes.py", "source_location": null, "source_url": null, "captured_at": null, "author": null, "contributor": null}, {"id": "routes_notifications_recent", "label": "notifications.recent", "file_type": "code", "source_file": "app/notifications/routes.py", "source_location": null, "source_url": null, "captured_at": null, "author": null, "contributor": null}, {"id": "routes_notifications_popups", "label": "notifications.popups", "file_type": "code", "source_file": "app/notifications/routes.py", "source_location": null, "source_url": null, "captured_at": null, "author": null, "contributor": null}, {"id": "routes_notifications_mark_read", "label": "notifications.mark_read", "file_type": "code", "source_file": "app/notifications/routes.py", "source_location": null, "source_url": null, "captured_at": null, "author": null, "contributor": null}, {"id": "routes_notifications_mark_all_read", "label": "notifications.mark_all_read", "file_type": "code", "source_file": "app/notifications/routes.py", "source_location": null, "source_url": null, "captured_at": null, "author": null, "contributor": null}, {"id": "routes_notifications_serialize", "label": "_serialize", "file_type": "code", "source_file": "app/notifications/routes.py", "source_location": null, "source_url": null, "captured_at": null, "author": null, "contributor": null}], "edges": [{"source": "routes_notifications_send", "target": "notification_notification", "relation": "shares_data_with", "confidence": "EXTRACTED", "confidence_score": 1.0, "source_file": "app/notifications/routes.py", "source_location": null, "weight": 1.0}, {"source": "routes_notifications_recent", "target": "routes_notifications_serialize", "relation": "calls", "confidence": "EXTRACTED", "confidence_score": 1.0, "source_file": "app/notifications/routes.py", "source_location": null, "weight": 1.0}, {"source": "routes_notifications_popups", "target": "routes_notifications_serialize", "relation": "calls", "confidence": "EXTRACTED", "confidence_score": 1.0, "source_file": "app/notifications/routes.py", "source_location": null, "weight": 1.0}, {"source": "routes_notifications_mark_read", "target": "notification_notification", "relation": "shares_data_with", "confidence": "EXTRACTED", "confidence_score": 1.0, "source_file": "app/notifications/routes.py", "source_location": null, "weight": 1.0}, {"source": "routes_notifications_mark_all_read", "target": "notification_notification", "relation": "shares_data_with", "confidence": "EXTRACTED", "confidence_score": 1.0, "source_file": "app/notifications/routes.py", "source_location": null, "weight": 1.0}], "hyperedges": [{"id": "notification_center_flow", "label": "Notification Center Flow", "nodes": ["notification_notification", "routes_notifications_recent", "routes_notifications_popups", "routes_notifications_mark_read", "js_index_notification_center"], "relation": "implement", "confidence": "EXTRACTED", "confidence_score": 1.0, "source_file": "app/notifications/routes.py"}]}